{
  "books": [
    {
    "name": "Incredible Steel Keyboard",
    "genre": "History",
    "date": "2019-09-21T09:51:29.258Z",
    "image": "https://picsum.photos/460/640",
    "author": {
      "name": "Beau Anderson",
      "gender": "female"
    }
  },
  {
    "name": "Rustic Cotton Chips",
    "genre": "Guide",
    "date": "2019-06-30T16:07:00.899Z",
    "image": "https://picsum.photos/460/640",
    "author": {
      "name": "Angelina Will",
      "gender": "female"
    }
  },
  {
    "name": "Awesome Frozen Pants",
    "genre": "Travel",
    "date": "2019-12-31T16:01:31.607Z",
    "image": "https://picsum.photos/460/640",
    "author": {
      "name": "Solon Treutel",
      "gender": "female"
    }
  },
  {
    "name": "Gorgeous Soft Mouse",
    "genre": "Children",
    "date": "2019-07-30T07:06:46.588Z",
    "image": "https://picsum.photos/460/640",
    "author": {
      "name": "Syble Stark",
      "gender": "male"
    }
  },
  {
    "name": "Generic Concrete Shirt",
    "genre": "Satire",
    "date": "2019-11-16T05:07:33.313Z",
    "image": "https://picsum.photos/460/640",
    "author": {
      "name": "Keon Heaney",
      "gender": "female"
    }
  },
  {
    "name": "Fantastic Frozen Shirt",
    "genre": "Children",
    "date": "2019-09-12T08:24:11.537Z",
    "image": "https://picsum.photos/460/640",
    "author": {
      "name": "Miss Lester Friesen",
      "gender": "female"
    }
  },
  {
    "name": "Unbranded Fresh Shoes",
    "genre": "Art",
    "date": "2019-02-19T20:35:23.941Z",
    "image": "https://picsum.photos/460/640",
    "author": {
      "name": "Roosevelt Zemlak",
      "gender": "male"
    }
  },
  {
    "name": "Handcrafted Rubber Gloves",
    "genre": "Health",
    "date": "2019-06-21T16:42:51.564Z",
    "image": "https://picsum.photos/460/640",
    "author": {
      "name": "Lavinia Kautzer",
      "gender": "male"
    }
  },
  {
    "name": "Generic Metal Chips",
    "genre": "History",
    "date": "2019-04-23T01:39:01.301Z",
    "image": "https://picsum.photos/460/640",
    "author": {
      "name": "Liza Gulgowski",
      "gender": "female"
    }
  },
  {
    "name": "Gorgeous Rubber Table",
    "genre": "History",
    "date": "2019-04-29T19:31:37.232Z",
    "image": "https://picsum.photos/460/640",
    "author": {
      "name": "Dr. Marco Trantow",
      "gender": "female"
    }
  },
  {
    "name": "Practical Frozen Gloves",
    "genre": "Mystery",
    "date": "2019-11-20T11:34:58.772Z",
    "image": "https://picsum.photos/460/640",
    "author": {
      "name": "Zakary Kuhlman",
      "gender": "female"
    }
  },
  {
    "name": "Handcrafted Concrete Tuna",
    "genre": "Drama",
    "date": "2020-01-24T11:44:33.621Z",
    "image": "https://picsum.photos/460/640",
    "author": {
      "name": "Leone Boehm",
      "gender": "male"
    }
  },
  {
    "name": "Handmade Granite Soap",
    "genre": "Science",
    "date": "2019-08-18T04:30:55.435Z",
    "image": "https://picsum.photos/460/640",
    "author": {
      "name": "Owen Hegmann",
      "gender": "male"
    }
  },
  {
    "name": "Handcrafted Plastic Car",
    "genre": "Comics",
    "date": "2019-10-13T01:57:54.451Z",
    "image": "https://picsum.photos/460/640",
    "author": {
      "name": "Mrs. Aylin Emard",
      "gender": "female"
    }
  },
  {
    "name": "Handmade Cotton Hat",
    "genre": "Travel",
    "date": "2019-02-16T14:24:21.428Z",
    "image": "https://picsum.photos/460/640",
    "author": {
      "name": "Dr. Jerome Dooley",
      "gender": "female"
    }
  },
  {
    "name": "Gorgeous Metal Bike",
    "genre": "Guide",
    "date": "2019-11-29T15:29:21.390Z",
    "image": "https://picsum.photos/460/640",
    "author": {
      "name": "Skye Muller",
      "gender": "male"
    }
  },
  {
    "name": "Fantastic Metal Chicken",
    "genre": "Satire",
    "date": "2019-07-13T01:46:21.928Z",
    "image": "https://picsum.photos/460/640",
    "author": {
      "name": "Jaiden Kunze",
      "gender": "male"
    }
  },
  {
    "name": "Gorgeous Concrete Ball",
    "genre": "History",
    "date": "2019-02-25T12:25:15.202Z",
    "image": "https://picsum.photos/460/640",
    "author": {
      "name": "Kenya Schuppe",
      "gender": "female"
    }
  },
  {
    "name": "Sleek Rubber Pants",
    "genre": "Drama",
    "date": "2019-06-16T16:04:18.304Z",
    "image": "https://picsum.photos/460/640",
    "author": {
      "name": "Adalberto Herman",
      "gender": "male"
    }
  },
  {
    "name": "Unbranded Fresh Sausages",
    "genre": "Mystery",
    "date": "2019-07-14T23:57:41.290Z",
    "image": "https://picsum.photos/460/640",
    "author": {
      "name": "Elton Swaniawski",
      "gender": "female"
    }
  },
  {
    "name": "Awesome Wooden Tuna",
    "genre": "Math",
    "date": "2019-11-04T08:41:41.278Z",
    "image": "https://picsum.photos/460/640",
    "author": {
      "name": "Sigurd Boyle",
      "gender": "male"
    }
  },
  {
    "name": "Licensed Concrete Keyboard",
    "genre": "Travel",
    "date": "2020-01-20T07:28:24.512Z",
    "image": "https://picsum.photos/460/640",
    "author": {
      "name": "Ashly Wintheiser",
      "gender": "male"
    }
  },
  {
    "name": "Awesome Metal Pants",
    "genre": "Art",
    "date": "2019-03-09T13:49:30.151Z",
    "image": "https://picsum.photos/460/640",
    "author": {
      "name": "Mariah Casper",
      "gender": "male"
    }
  },
  {
    "name": "Handmade Concrete Shoes",
    "genre": "Horror",
    "date": "2019-11-11T03:37:15.360Z",
    "image": "https://picsum.photos/460/640",
    "author": {
      "name": "Vicky Hills",
      "gender": "female"
    }
  },
  {
    "name": "Gorgeous Granite Salad",
    "genre": "History",
    "date": "2020-01-14T10:07:20.853Z",
    "image": "https://picsum.photos/460/640",
    "author": {
      "name": "Evert Hahn",
      "gender": "female"
    }
  },
  {
    "name": "Small Plastic Keyboard",
    "genre": "Science",
    "date": "2020-01-09T03:09:34.743Z",
    "image": "https://picsum.photos/460/640",
    "author": {
      "name": "Isabelle Sanford",
      "gender": "male"
    }
  }
],
  "genres": ["Horror", "Finance", "Comics", "Fantasy", "Math", "Guide", "Satire", "Poetry", "Children", "Art", "Romance", "History", "Health", "Mystery"]
}
